rwa_wdm/__init__.py
rwa_wdm/__main__.py
rwa_wdm/io.py
rwa_wdm/sim.py
rwa_wdm/util.py
rwa_wdm/net/__init__.py
rwa_wdm/net/arpa.py
rwa_wdm/net/clara.py
rwa_wdm/net/italian.py
rwa_wdm/net/janet.py
rwa_wdm/net/net.py
rwa_wdm/net/nsf.py
rwa_wdm/net/rnp.py
rwa_wdm/rwa/__init__.py
rwa_wdm/rwa/rwa.py
rwa_wdm/rwa/ga/__init__.py
rwa_wdm/rwa/ga/chromo.py
rwa_wdm/rwa/ga/env.py
rwa_wdm/rwa/ga/ga.py
rwa_wdm/rwa/ga/pop.py
rwa_wdm/rwa/ga/utils.py
rwa_wdm/rwa/routing/__init__.py
rwa_wdm/rwa/routing/dijkstra.py
rwa_wdm/rwa/routing/yen.py
rwa_wdm/rwa/wlassignment/__init__.py
rwa_wdm/rwa/wlassignment/ff.py
rwa_wdm/rwa/wlassignment/rf.py
rwa_wdm/rwa/wlassignment/vcolor.py
rwa_wdm-0.2.3.dist-info/LICENSE
rwa_wdm-0.2.3.dist-info/METADATA
rwa_wdm-0.2.3.dist-info/WHEEL
rwa_wdm-0.2.3.dist-info/top_level.txt
rwa_wdm-0.2.3.dist-info/RECORD
