Metadata-Version: 2.1
Name: rwa-wdm
Version: 0.2.3
Summary: Routing and wavelength assignment simulator over WDM networks
Home-page: https://github.com/cassiobatista/rwa-wdm-sim
Author: Cassio Batista
Author-email: cassiotb@ufpa.br
License: GPL
Platform: UNKNOWN
Requires-Python: >=3.7
Requires-Dist: argcomplete
Requires-Dist: networkx
Requires-Dist: numpy
Requires-Dist: matplotlib
